doubleplusungood/__init__.py
doubleplusungood-0.1.dist-info/METADATA
doubleplusungood-0.1.dist-info/WHEEL
doubleplusungood-0.1.dist-info/entry_points.txt
doubleplusungood-0.1.dist-info/top_level.txt
doubleplusungood-0.1.dist-info/zip-safe
doubleplusungood-0.1.dist-info/RECORD
