Metadata-Version: 2.1
Name: doubleplusungood
Version: 0.1
Summary: Shameless name-grab for a possible future project
Home-page: https://github.com/con-f-use/doubleplusungood
Author: con-f-use
Author-email: con-f-use@gmx.net
License: UNKNOWN
Platform: UNKNOWN
Classifier: Environment :: Console
Classifier: Intended Audience :: End Users/Desktop
Classifier: Operating System :: OS Independent
Classifier: Programming Language :: Python
Classifier: Topic :: Desktop Environment
Classifier: Topic :: System :: Shells
Classifier: Topic :: System :: System Shells
